AUTHORS.md
CHANGELOG.md
CONTRIBUTING.md
LICENSE
MANIFEST.in
README.md
setup.py
docs/html/_static/ajax-loader.gif
docs/html/_static/comment-bright.png
docs/html/_static/comment-close.png
docs/html/_static/comment.png
docs/html/_static/down-pressed.png
docs/html/_static/down.png
docs/html/_static/file.png
docs/html/_static/minus.png
docs/html/_static/plus.png
docs/html/_static/robot.png
docs/html/_static/up-pressed.png
docs/html/_static/up.png
docs/html/_static/img/robot-highres.png
docs/html/_static/img/robot.png
docs/html/_static/img/whedon-before.png
docs/html/_static/img/whedon-upgrade.png
docs/img/robot-highres.png
docs/img/robot.png
docs/img/whedon-before.png
docs/img/whedon-upgrade.png
tests/__init__.py
tests/test_papers.py
tests/paper/Makefile
tests/paper/latex.template
tests/paper/logo.png
tests/paper/paper.bib
tests/paper/paper.md
tests/paper/paper.pdf
tests/paper/paper.tex
tests/paper/img/expfactory.png
tests/paper/img/portal.png
whedon/__init__.py
whedon/version.py
whedon.egg-info/PKG-INFO
whedon.egg-info/SOURCES.txt
whedon.egg-info/dependency_links.txt
whedon.egg-info/entry_points.txt
whedon.egg-info/not-zip-safe
whedon.egg-info/requires.txt
whedon.egg-info/top_level.txt
whedon/cli/__init__.py
whedon/cli/paper.py
whedon/cli/shell.py
whedon/logger/__init__.py
whedon/logger/message.py
whedon/logger/progress.py
whedon/logger/spinner.py
whedon/main/__init__.py
whedon/main/paper.py
whedon/main/base/__init__.py
whedon/main/base/command.py
whedon/main/base/flags.py
whedon/main/base/generate.py
whedon/main/base/logger.py
whedon/utils/__init__.py
whedon/utils/fileio.py
whedon/utils/terminal.py
whedon/utils/web.py