Metadata-Version: 1.1
Name: whedon
Version: 0.0.2
Summary: whedon python helper functions for https://openbases.github.io
Home-page: http://www.github.com/openbases/whedon-python
Author: Vanessa Sochat
Author-email: vsochat@stanford.edu
License: LICENSE
Keywords: whedon,markdown,pandoc
Platform: UNKNOWN
Classifier: Intended Audience :: Science/Research
Classifier: Intended Audience :: Developers
Classifier: Programming Language :: Python
Classifier: Topic :: Software Development
Classifier: Topic :: Scientific/Engineering
Classifier: Operating System :: Unix
Classifier: Programming Language :: Python :: 2.7
Classifier: Programming Language :: Python :: 3
